Metadata-Version: 2.1
Name: geog510-test
Version: 0.0.1
Summary: test for course Geog510
Home-page: https://github.com/Feng96/geog510-test
Author: Yinan Feng
Author-email: 1041267458@qq.com
License: MIT license
Keywords: geog_test
Classifier: Development Status :: 2 - Pre-Alpha
Classifier: Intended Audience :: Developers
Classifier: License :: OSI Approved :: MIT License
Classifier: Natural Language :: English
Classifier: Programming Language :: Python :: 3
Classifier: Programming Language :: Python :: 3.7
Classifier: Programming Language :: Python :: 3.8
Classifier: Programming Language :: Python :: 3.9
Classifier: Programming Language :: Python :: 3.10
Requires-Python: >=3.7
License-File: LICENSE
